musical_games/__init__.py
musical_games/__version__.py
musical_games/utils.py
musical_games/data/__init__.py
musical_games/data/dice_games/__init__.py
musical_games/data/dice_games/calegari_aria/__init__.py
musical_games/data/dice_games/calegari_aria/bars_aria.csv
musical_games/data/dice_games/calegari_aria/lilypond/bar_overview.ly
musical_games/data/dice_games/calegari_aria/lilypond/composition_midi.ly
musical_games/data/dice_games/calegari_aria/lilypond/composition_pdf.ly
musical_games/data/dice_games/calegari_aria/lilypond/single_bar.ly
musical_games/data/dice_games/calegari_aria/lilypond/single_dice_table_element.ly
musical_games/data/dice_games/cpe_bach_counterpoint/__init__.py
musical_games/data/dice_games/cpe_bach_counterpoint/bars_bass.csv
musical_games/data/dice_games/cpe_bach_counterpoint/bars_treble.csv
musical_games/data/dice_games/cpe_bach_counterpoint/lilypond/bar_overview.ly
musical_games/data/dice_games/cpe_bach_counterpoint/lilypond/composition_midi.ly
musical_games/data/dice_games/cpe_bach_counterpoint/lilypond/composition_pdf.ly
musical_games/data/dice_games/cpe_bach_counterpoint/lilypond/single_bar.ly
musical_games/data/dice_games/cpe_bach_counterpoint/lilypond/single_dice_table_element.ly
musical_games/data/dice_games/gerlach_scottish_dance/__init__.py
musical_games/data/dice_games/gerlach_scottish_dance/scottish_dance_bars.csv
musical_games/data/dice_games/gerlach_scottish_dance/scottish_dance_bars_annotations.csv
musical_games/data/dice_games/gerlach_scottish_dance/lilypond/bar_overview.ly
musical_games/data/dice_games/gerlach_scottish_dance/lilypond/composition_midi.ly
musical_games/data/dice_games/gerlach_scottish_dance/lilypond/composition_pdf.ly
musical_games/data/dice_games/gerlach_scottish_dance/lilypond/single_bar.ly
musical_games/data/dice_games/gerlach_scottish_dance/lilypond/single_dice_table_element.ly
musical_games/data/dice_games/kirnberger_menuet_trio/__init__.py
musical_games-0.9.2.dist-info/entry_points.txt
musical_games-0.9.2.dist-info/LICENSE
musical_games-0.9.2.dist-info/WHEEL
musical_games-0.9.2.dist-info/METADATA
musical_games-0.9.2.dist-info/RECORD
