Metadata-Version: 2.3
Name: musical_games
Version: 0.9.2
Summary: Implementation of musical dice games from the 18th century.
Keywords: Musical games,Dice games,Piano music
Author-email: Robbert Harms <robbert@xkls.nl>
Requires-Python: >=3.12
Classifier: Development Status :: 5 - Production/Stable
Classifier: Environment :: Console
Classifier: Intended Audience :: Education
Classifier: Intended Audience :: Science/Research
Classifier: Natural Language :: English
Classifier: License :: OSI Approved :: GNU Lesser General Public License v3 (LGPLv3)
Classifier: Programming Language :: Python :: 3.12
Classifier: Topic :: Scientific/Engineering
Requires-Dist: Jinja2~=3.1.5
Requires-Dist: frozendict~=2.4.6
Requires-Dist: sphinx~=7.2.6 ; extra == "doc"
Requires-Dist: git-cliff~=2.8.0 ; extra == "doc"
Requires-Dist: pytest~=8.0.2 ; extra == "test"
Requires-Dist: pytest-check~=2.3.1 ; extra == "test"
Requires-Dist: pytest-cov~=4.1.0 ; extra == "test"
Requires-Dist: pytest-html~=4.1.1 ; extra == "test"
Requires-Dist: tox~=4.14.1 ; extra == "test"
Project-URL: homepage, https://github.com/robbert-harms/musical-games
Provides-Extra: doc
Provides-Extra: test
